TrojanPayload/TrojanHorse.py
TrojanPayload/__init__.py
TrojanPayload/client_code.py
TrojanPayload/server_code.py
PythonTrojanHorse-0.1.dist-info/LICENSE.txt
PythonTrojanHorse-0.1.dist-info/METADATA
PythonTrojanHorse-0.1.dist-info/WHEEL
PythonTrojanHorse-0.1.dist-info/top_level.txt
PythonTrojanHorse-0.1.dist-info/RECORD
